ProdPack/__init__.py
ProdPack/model.py
ProdPack/prod.py
prodpack-0.1.1.dist-info/METADATA
prodpack-0.1.1.dist-info/WHEEL
prodpack-0.1.1.dist-info/licenses/LICENSE
prodpack-0.1.1.dist-info/RECORD
