Metadata-Version: 2.3
Name: ProdPack
Version: 0.1.1
Summary: An Efficiency and Productivity Analysis Package
Project-URL: Homepage, https://github.com/daopingw/ProdPack
Project-URL: Bug Tracker, https://github.com/daopingw/ProdPack/issues
Author-email: Dr Daoping Wang <daopingwang@outlook.com>
License: MIT License
License-File: LICENSE
Classifier: Intended Audience :: Science/Research
Classifier: License :: OSI Approved :: MIT License
Classifier: Operating System :: OS Independent
Classifier: Programming Language :: Python :: 3
Requires-Python: >=3.6
Requires-Dist: deapack>=0.1.3
Requires-Dist: numpy>=1.26.0
Requires-Dist: pandas>=1.3.5
Requires-Dist: pulp>=2.6.0
